odoo/addons/procurement_auto_create_group_carrier/README.rst
odoo/addons/procurement_auto_create_group_carrier/__init__.py
odoo/addons/procurement_auto_create_group_carrier/__manifest__.py
odoo/addons/procurement_auto_create_group_carrier/i18n/it.po
odoo/addons/procurement_auto_create_group_carrier/i18n/procurement_auto_create_group_carrier.pot
odoo/addons/procurement_auto_create_group_carrier/i18n/pt_BR.po
odoo/addons/procurement_auto_create_group_carrier/models/__init__.py
odoo/addons/procurement_auto_create_group_carrier/models/stock_rule.py
odoo/addons/procurement_auto_create_group_carrier/readme/CONTRIBUTORS.md
odoo/addons/procurement_auto_create_group_carrier/readme/CREDITS.md
odoo/addons/procurement_auto_create_group_carrier/readme/DESCRIPTION.md
odoo/addons/procurement_auto_create_group_carrier/static/description/icon.png
odoo/addons/procurement_auto_create_group_carrier/static/description/index.html
odoo/addons/procurement_auto_create_group_carrier/tests/__init__.py
odoo/addons/procurement_auto_create_group_carrier/tests/test_procurement_auto_create_group_carrier.py
odoo_addon_procurement_auto_create_group_carrier-18.0.1.0.0.3.dist-info/METADATA
odoo_addon_procurement_auto_create_group_carrier-18.0.1.0.0.3.dist-info/WHEEL
odoo_addon_procurement_auto_create_group_carrier-18.0.1.0.0.3.dist-info/top_level.txt
odoo_addon_procurement_auto_create_group_carrier-18.0.1.0.0.3.dist-info/RECORD
